Metadata-Version: 1.0
Name: ok-distri
Version: 0.1
Summary: Gaussian distributions
Home-page: UNKNOWN
Author: Princewill Okechukwu
Author-email: okechukwuprincewillw@gmail.com
License: UNKNOWN
Platform: UNKNOWN
